pybga/__init__.py
pybga/pins_bga.py
pybga-0.6.dist-info/METADATA
pybga-0.6.dist-info/WHEEL
pybga-0.6.dist-info/top_level.txt
pybga-0.6.dist-info/RECORD
