Metadata-Version: 2.1
Name: pybga
Version: 0.6
Summary: useful to make pins into Altium component lib
Home-page: UNKNOWN
Author: Nikita Kuzin
Author-email: getsense@yandex.ru
License: UNKNOWN
Platform: UNKNOWN
Classifier: Programming Language :: Python :: 3
Classifier: License :: Freeware
Classifier: Operating System :: OS Independent
